retackAI_sdk/__init__.py
retackAI_sdk/retack_client.py
retack_sdk_django-1.0.2.dist-info/LICENSE
retack_sdk_django-1.0.2.dist-info/METADATA
retack_sdk_django-1.0.2.dist-info/WHEEL
retack_sdk_django-1.0.2.dist-info/top_level.txt
retack_sdk_django-1.0.2.dist-info/RECORD
