Metadata-Version: 2.1
Name: retack-sdk-django
Version: 1.0.2
Summary: Retack SDK for Django
Author: Truenary
Author-email: ramesh.shrestha@truenary.com
License: MIT
License-File: LICENSE
Requires-Dist: requests
